dmd/__init__.py
dmd/__main__.py
dmd/core.py
dmd/extensions.py
dmd/templates/main.html
dmd-0.1.7.data/scripts/dmd
dmd-0.1.7.dist-info/LICENSE
dmd-0.1.7.dist-info/METADATA
dmd-0.1.7.dist-info/WHEEL
dmd-0.1.7.dist-info/top_level.txt
dmd-0.1.7.dist-info/RECORD
